bigvgan/__init__.py
bigvgan/activations.py
bigvgan/bigvgan.py
bigvgan/discriminators.py
bigvgan/env.py
bigvgan/inference.py
bigvgan/inference_e2e.py
bigvgan/loss.py
bigvgan/meldataset.py
bigvgan/train.py
bigvgan/utils.py
bigvgan/alias_free_activation/cuda/__init__.py
bigvgan/alias_free_activation/cuda/activation1d.py
bigvgan/alias_free_activation/cuda/anti_alias_activation.cpp
bigvgan/alias_free_activation/cuda/anti_alias_activation_cuda.cu
bigvgan/alias_free_activation/cuda/compat.h
bigvgan/alias_free_activation/cuda/load.py
bigvgan/alias_free_activation/cuda/type_shim.h
bigvgan/alias_free_activation/torch/__init__.py
bigvgan/alias_free_activation/torch/act.py
bigvgan/alias_free_activation/torch/filter.py
bigvgan/alias_free_activation/torch/resample.py
bigvgan-2.4.1.dist-info/METADATA
bigvgan-2.4.1.dist-info/WHEEL
bigvgan-2.4.1.dist-info/licenses/LICENSE
bigvgan-2.4.1.dist-info/RECORD
