Metadata-Version: 2.3
Name: bigvgan
Version: 2.4.1
Author: NVIDIA
License-File: LICENSE
Requires-Python: >=3.10
Requires-Dist: auraloss
Requires-Dist: huggingface-hub>=0.23.4
Requires-Dist: librosa>=0.8.1
Requires-Dist: matplotlib
Requires-Dist: ninja
Requires-Dist: nnaudio
Requires-Dist: numpy
Requires-Dist: pesq
Requires-Dist: scipy
Requires-Dist: soundfile
Requires-Dist: tensorboard
Requires-Dist: torch
Requires-Dist: tqdm
